[
    {
        "name": "Jeyaparan Senthurvelautham",
        "birthday": "20-02-2000",
        "email": "sjeyaparan3@gmail.com"
    },
    {
        "name": "Udyoga",
        "birthday": "13-12-2002",
        "email": "udyoga2002@gmail.com"
    },
    {
        "name": "Tharindu Dehigaspitiyage",
        "birthday": "17-09-1998",
        "email": "dehigaspitiyagedontharindu@gmail.com"
    },
    {
        "name": "Ashen Mark",
        "birthday": "06-07-2001",
        "email": "ashenmark5@gmail.com"
    },
    {
        "name": "Kushan Malith",
        "birthday": "27-01-2000",
        "email": "kushan1111111111@gmail.com"
    },
    {
        "name": "Kalika Sharith",
        "birthday": "08-02-2000",
        "email": "kalika.sharith@gmail.com"
    },
    {
        "name": "Deshan Peiris",
        "birthday": "30-05-2000",
        "email": "deshanpeiris444@gmail.com"
    },
    {
        "name": "Kajendran Rajeevan",
        "birthday": "23-02-2000",
        "email": "rajeevan.kajan@gmail.com"
    },
    {
        "name": "Mamuna Raheem",
        "birthday": "14-04-1998",
        "email": "abdulraheem0620@icloud.com"
    },
    {
        "name": "Sheik Ibrahim",
        "birthday": "18-11-2003",
        "email": "sheikibrahim@programmer.net"
    },
    {
        "name": "Aasif",
        "birthday": "19-08-2003",
        "email": "aasiffiraz178@gmail.com"
    },
    {
        "name": "Hatski Wijewickrama",
        "birthday": "26-09-2003",
        "email": "hatskiwijewickrama@gmail.com"
    },
    {
        "name": "Sonal Perera",
        "birthday": "24-05-2003",
        "email": "insane40x@gmail.com"
    },
    {
        "name": "Ammar",
        "birthday": "14-07-2002",
        "email": "ammaaradn2@gmail.com"
    },
    {
        "name": "Chamindu",
        "birthday": "24-01-1999",
        "email": "chamindu112@gmail.com"
    },
    {
        "name": "Siyan",
        "birthday": "25-05-2001",
        "email": "mohammedsiyan10@gmail.com"
    },
    {
        "name": "Sandali Kariyawasam",
        "birthday": "09-10-1999",
        "email": "sadakariyawasam2@gmail.com"
    },
    {
        "name": "Hansani Sandaruwani",
        "birthday": "17-04-1998",
        "email": "sandaruwani98peiris@gmail.com"
    },
    {
        "name": "Piyumi Sathsarani",
        "birthday": "25-07-1999",
        "email": "piyumiduleka0@gmail.com"
    },
    {
        "name": "Dinushika Sandeepani",
        "birthday": "14-11-1999",
        "email": "hansanidinelka1012@gmail.com"
    },
    {
        "name": "Samadhi Fernando",
        "birthday": "29-12-1998",
        "email": "samadhifernando00@gmail.com"
    },
    {
        "name": "Mishel Premachandra",
        "birthday": "25-05-1998",
        "email": "sachipro1998@gmail.com"
    },
    {
        "name": "Chamod Fernando",
        "birthday": "08-03-2000",
        "email": "hasarangafernando@gmail.com"
    },
    {
        "name": "Dinithi Gunasekara",
        "birthday": "15-09-2000",
        "email": "dinithigunasekara2@gmail.com"
    },
    {
        "name": "Aveen  Kularathne",
        "birthday": "16-10-2000",
        "email": "aveenrk@gmail.com"
    },
    {
        "name": "Yohaan Sivaneshan",
        "birthday": "11-11-1999",
        "email": "yohaanfabs@gmail.com"
    },
    {
        "name": "Navith Fernando",
        "birthday": "29-05-1999",
        "email": "knfernando2k@gmail.com"
    },
    {
        "name": "Nuwan Senevirathne",
        "birthday": "01-04-1993",
        "email": "smpg.nuwan@gmail.com"
    },
    {
        "name": "Reshma Rajeshkannan",
        "birthday": "03-05-2001",
        "email": "rajeshkannanreshma@gmail.com"
    },
    {
        "name": "Kaviya Kannapiran",
        "birthday": "09-06-2002",
        "email": "kaviyakannapiran@gmail.com"
    },
    {
        "name": "Ladumisha Perinbanayagam",
        "birthday": "11-01-2003",
        "email": "ladunayagam321@gmail.com"
    },
    {
        "name": "Rachel Coonghe",
        "birthday": "12-08-2003",
        "email": "edison@citycable.lk"
    },
    {
        "name": "Nipuni Wasundara",
        "birthday": "19-11-1998",
        "email": "nipuniwasundara15@gmail.com"
    }
]
